CHANGELOG.txt
LICENCE.txt
MANIFEST.in
README.txt
setup.py
modelfunction/__init__.py
modelfunction.egg-info/PKG-INFO
modelfunction.egg-info/SOURCES.txt
modelfunction.egg-info/dependency_links.txt
modelfunction.egg-info/top_level.txt