Metadata-Version: 1.1
Name: modelfunction
Version: 0.0.3
Summary: Extract model function
Home-page: UNKNOWN
Author: Suheda Seyhan
Author-email: suhedaseyhan@hotmail.com
License: MIT
Keywords: model
Platform: UNKNOWN
Classifier: Development Status :: 5 - Production/Stable
Classifier: Intended Audience :: Education
Classifier: Operating System :: Microsoft :: Windows :: Windows 10
Classifier: License :: OSI Approved :: MIT License
Classifier: Programming Language :: Python :: 3
